ptCryptoClub/__init__.py
ptCryptoClub/app.py
ptCryptoClub-1.0.0.dist-info/LICENSE
ptCryptoClub-1.0.0.dist-info/METADATA
ptCryptoClub-1.0.0.dist-info/WHEEL
ptCryptoClub-1.0.0.dist-info/top_level.txt
ptCryptoClub-1.0.0.dist-info/RECORD
